django_template_shortcuts-0.2.2.dist-info/DESCRIPTION.rst
django_template_shortcuts-0.2.2.dist-info/METADATA
django_template_shortcuts-0.2.2.dist-info/RECORD
django_template_shortcuts-0.2.2.dist-info/WHEEL
django_template_shortcuts-0.2.2.dist-info/metadata.json
django_template_shortcuts-0.2.2.dist-info/pbr.json
django_template_shortcuts-0.2.2.dist-info/top_level.txt
template_shortcuts/__init__.py
template_shortcuts/models.py
template_shortcuts/nodes.py
template_shortcuts/providers/__init__.py
template_shortcuts/providers/cdnjs.py
template_shortcuts/providers/google.py
template_shortcuts/providers/provider.py
template_shortcuts/templatetags/__init__.py
template_shortcuts/templatetags/shortcuts.py
