Metadata-Version: 2.0
Name: django-template-shortcuts
Version: 0.2.2
Summary: Reusable Django templatetags
Home-page: https://github.com/comandrei/django-template-shortcuts/
Author: Andrei Coman
Author-email: comandrei@gmail.com
License: BSD
Platform: UNKNOWN
Classifier: Development Status :: 3 - Alpha
Classifier: Environment :: Web Environment
Classifier: Framework :: Django
Classifier: Intended Audience :: Developers
Classifier: License :: OSI Approved :: BSD License
Classifier: Operating System :: OS Independent
Classifier: Programming Language :: Python
Classifier: Topic :: Software Development :: Libraries :: Python Modules
Classifier: Topic :: Utilities
Requires-Dist: django (>=1.7)
